jinjanator_plugins/__init__.py
jinjanator_plugins/py.typed
jinjanator_plugins-25.1.0.dist-info/METADATA
jinjanator_plugins-25.1.0.dist-info/WHEEL
jinjanator_plugins-25.1.0.dist-info/licenses/LICENSE
jinjanator_plugins-25.1.0.dist-info/RECORD
