Metadata-Version: 2.3
Name: jinjanator-plugins
Version: 25.1.0
Summary: Package which provides the plugin API for the jinjanator tool
Project-URL: Bug Tracker, https://github.com/kpfleming/jinjanator-plugins/issues
Project-URL: Homepage, https://github.com/kpfleming/jinjanator-plugins
Author-email: "Kevin P. Fleming" <jinjanator@kevin.km6g.us>
License: Apache-2.0
Classifier: Development Status :: 5 - Production/Stable
Classifier: Environment :: Console
Classifier: Intended Audience :: Developers
Classifier: Intended Audience :: System Administrators
Classifier: Natural Language :: English
Classifier: Operating System :: OS Independent
Classifier: Programming Language :: Python :: 3 :: Only
Classifier: Programming Language :: Python :: 3.10
Classifier: Programming Language :: Python :: 3.11
Classifier: Programming Language :: Python :: 3.12
Classifier: Programming Language :: Python :: 3.13
Classifier: Programming Language :: Python :: 3.14
Classifier: Typing :: Typed
Requires-Python: >=3.10
Requires-Dist: attrs
Requires-Dist: pluggy
Requires-Dist: typing-extensions
